psdm/__init__.py
psdm/base.py
psdm/meta.py
psdm/py.typed
psdm/quantities/__init__.py
psdm/quantities/multi_phase.py
psdm/quantities/single_phase.py
psdm/steadystate_case/__init__.py
psdm/steadystate_case/active_power.py
psdm/steadystate_case/case.py
psdm/steadystate_case/characteristic.py
psdm/steadystate_case/controller.py
psdm/steadystate_case/external_grid.py
psdm/steadystate_case/load.py
psdm/steadystate_case/reactive_power.py
psdm/steadystate_case/transformer.py
psdm/topology/__init__.py
psdm/topology/branch.py
psdm/topology/coupler.py
psdm/topology/external_grid.py
psdm/topology/fuse.py
psdm/topology/load.py
psdm/topology/load_model.py
psdm/topology/node.py
psdm/topology/switch.py
psdm/topology/topology.py
psdm/topology/transformer.py
psdm/topology/windings.py
psdm/topology_case/__init__.py
psdm/topology_case/case.py
psdm/topology_case/element_state.py
ieeh_power_system_data_model-2.3.3.dist-info/METADATA
ieeh_power_system_data_model-2.3.3.dist-info/WHEEL
ieeh_power_system_data_model-2.3.3.dist-info/licenses/AUTHORS.md
ieeh_power_system_data_model-2.3.3.dist-info/licenses/LICENSE
ieeh_power_system_data_model-2.3.3.dist-info/RECORD
