Metadata-Version: 2.4
Name: ieeh-power-system-data-model
Version: 2.3.3
Summary: A data model for describing power systems
Project-URL: Source, https://github.com/ieeh-tu-dresden/power-system-data-model
Author-email: Sasan Jacob Rasti <sasan_jacob.rasti@tu-dresden.de>, Sebastian Krahmer <sebastian.krahmer@tu-dresden.de>, Laura Fiedler <laura.fiedler1@tu-dresden.de>, Maximilian Schmidt <maximilian.schmidt@tu-dresden.de>
License: BSD 3-Clause License
License-File: AUTHORS.md
License-File: LICENSE
Requires-Python: >=3.10
Requires-Dist: loguru>=0.7.3
Requires-Dist: pydantic>=2.10.6
